cvsser/__init__.py
cvsser/cvss.py
cvsser/cvss_guide.py
tests/__init__.py
tests/test_vectorstring.py
cvsser-1.1.0.dist-info/LICENSE
cvsser-1.1.0.dist-info/METADATA
cvsser-1.1.0.dist-info/WHEEL
cvsser-1.1.0.dist-info/top_level.txt
cvsser-1.1.0.dist-info/RECORD
